AutoPackager/code/JackkillianAutoPackager.py
AutoPackager/code/__init__.py
JackkillianAutoPackager-1.0.2.dist-info/LICENSE
JackkillianAutoPackager-1.0.2.dist-info/METADATA
JackkillianAutoPackager-1.0.2.dist-info/WHEEL
JackkillianAutoPackager-1.0.2.dist-info/top_level.txt
JackkillianAutoPackager-1.0.2.dist-info/RECORD
